receive_sms/__init__.py
receive_sms-1.0.4.dist-info/LICENSE.txt
receive_sms-1.0.4.dist-info/METADATA
receive_sms-1.0.4.dist-info/WHEEL
receive_sms-1.0.4.dist-info/top_level.txt
receive_sms-1.0.4.dist-info/RECORD
