Metadata-Version: 2.1
Name: receive-sms
Version: 1.0.4
Summary: Receive SMS
Home-page: https://github.com/Emilien-B/receive-sms
Author: EmilienB
Author-email: emilien.barde@gmail.com
License: UNKNOWN
Keywords: python,python3,sms,receive,message,free,unlimited,scraping
Platform: UNKNOWN
Classifier: Intended Audience :: Developers
Classifier: Programming Language :: Python :: 3
Classifier: License :: OSI Approved :: MIT License
Classifier: Operating System :: Unix
Classifier: Operating System :: MacOS :: MacOS X
Classifier: Operating System :: Microsoft :: Windows
License-File: LICENSE.txt
Requires-Dist: requests
